adafruit_circuitpython_prompt_toolkit-1.0.6.dist-info/licenses/LICENSE
adafruit_prompt_toolkit/__init__.py
adafruit_prompt_toolkit/history.py
adafruit_circuitpython_prompt_toolkit-1.0.6.dist-info/METADATA
adafruit_circuitpython_prompt_toolkit-1.0.6.dist-info/WHEEL
adafruit_circuitpython_prompt_toolkit-1.0.6.dist-info/top_level.txt
adafruit_circuitpython_prompt_toolkit-1.0.6.dist-info/RECORD
