Metadata-Version: 2.4
Name: adafruit-circuitpython-prompt-toolkit
Version: 1.0.6
Summary: Slimmed down implementation of prompt_toolkit for CircuitPython
Author-email: Adafruit Industries <circuitpython@adafruit.com>
License: MIT
Project-URL: Homepage, https://github.com/adafruit/Adafruit_CircuitPython_Prompt_Toolkit
Keywords: adafruit,blinka,circuitpython,micropython,prompt_toolkit
Classifier: Intended Audience :: Developers
Classifier: Topic :: Software Development :: Libraries
Classifier: Topic :: Software Development :: Embedded Systems
Classifier: Topic :: System :: Hardware
Classifier: License :: OSI Approved :: MIT License
Classifier: Programming Language :: Python :: 3
License-File: LICENSE
Requires-Dist: Adafruit-Blinka
Provides-Extra: optional
Dynamic: license-file
